LICENSE
MANIFEST.in
README.rst
VERSION
setup.cfg
setup.py
flask_opentracing/__init__.py
flask_opentracing/scope_manager.py
flask_opentracing/tracing.py
signalfx_instrumentation_flask.egg-info/PKG-INFO
signalfx_instrumentation_flask.egg-info/SOURCES.txt
signalfx_instrumentation_flask.egg-info/dependency_links.txt
signalfx_instrumentation_flask.egg-info/not-zip-safe
signalfx_instrumentation_flask.egg-info/requires.txt
signalfx_instrumentation_flask.egg-info/top_level.txt
tests/__init__.py
tests/test_flask_api.py
tests/test_flask_tracing.py