Metadata-Version: 2.1
Name: signalfx-instrumentation-flask
Version: 1.2.0
Summary: OpenTracing support for Flask applications
Home-page: http://github.com/signalfx/python-flask
Author: SignalFx, Inc.
Author-email: signalfx-oss@splunk.com
License: BSD
Download-URL: https://github.com/signalfx/python-flask/tarball/1.2.0
Platform: any
Classifier: Environment :: Web Environment
Classifier: Intended Audience :: Developers
Classifier: License :: OSI Approved :: BSD License
Classifier: Operating System :: OS Independent
Classifier: Programming Language :: Python
Classifier: Programming Language :: Python :: 2
Classifier: Programming Language :: Python :: 2.7
Classifier: Programming Language :: Python :: 3
Classifier: Programming Language :: Python :: 3.5
Classifier: Programming Language :: Python :: 3.6
Classifier: Programming Language :: Python :: 3.7
Classifier: Programming Language :: Python :: 3.8
Classifier: Programming Language :: Python :: Implementation :: CPython
Classifier: Programming Language :: Python :: Implementation :: PyPy
Classifier: Topic :: Internet :: WWW/HTTP :: Dynamic Content
Classifier: Topic :: Software Development :: Libraries :: Python Modules
Provides-Extra: tests
